[
  {
    "order_number": "1",
    "customer_name": "Kivell",
    "status": "Accepted",
    "category": "Electronics",
    "country": "United Kingdom",
    "created_date": "1/23/2019"
  },
  {
    "order_number": "2",
    "customer_name": "Jardine",
    "status": "Processing",
    "category": "Furniture",
    "country": "Russia",
    "created_date": "2/9/2019"
  },
  {
    "order_number": "3",
    "customer_name": "Gill",
    "status": "Rejected",
    "category": "Stationery",
    "country": "German",
    "created_date": "2/26/2019"
  },
  {
    "order_number": "4",
    "customer_name": "Sor’vino",
    "status": "Open",
    "category": "Furniture",
    "country": "Singapore",
    "created_date": "3/15/2019"
  },
  {
    "order_number": "5",
    "customer_name": "Jones",
    "status": "Rejected",
    "category": "Sports",
    "country": "German",
    "created_date": "4/1/2019"
  },
  {
    "order_number": "6",
    "customer_name": "Andrews",
    "status": "Processing",
    "category": "Electronics",
    "country": "Malaysia",
    "created_date": "4/18/2019"
  },
  {
    "order_number": "7",
    "customer_name": "Jardine",
    "status": "Processing",
    "category": "Sports",
    "country": "German",
    "created_date": "5/5/2019"
  },
  {
    "order_number": "8",
    "customer_name": "Thompson",
    "status": "Accepted",
    "category": "Sports",
    "country": "Malaysia",
    "created_date": "5/22/2019"
  },
  {
    "order_number": "9",
    "customer_name": "Jones",
    "status": "Open",
    "category": "Furniture",
    "country": "Taiwan",
    "created_date": "6/8/2019"
  },
  {
    "order_number": "10",
    "customer_name": "Morgan",
    "status": "Processing",
    "category": "Sports",
    "country": "China",
    "created_date": "4/18/2019"
  }
]